{
  "id": "cp_544bcf974319",
  "workflow_id": "wf_952cb3b12794",
  "definition_id": "multi-step-test",
  "current_step": "step2",
  "completed_steps": [
    "step2",
    "step1"
  ],
  "step_outputs": {
    "step1": {
      "success": false,
      "error": "Handler not found: "
    },
    "step2": {
      "success": false,
      "error": "Handler not found: "
    }
  },
  "context_state": {
    "inputs": {},
    "state": {},
    "metadata": {}
  },
  "created_at": "2026-01-20T18:38:05.533930+00:00",
  "checksum": "ea3e195f4f6b24dc",
  "checkpoint_id": "wf_952cb3b12794_20260120_123805"
}